prefect_event_process/__init__.py
prefect_event_process/_version.py
prefect_event_process/worker.py
prefect_event_process-0.2.3.dist-info/licenses/LICENSE
prefect_event_process-0.2.3.dist-info/METADATA
prefect_event_process-0.2.3.dist-info/WHEEL
prefect_event_process-0.2.3.dist-info/entry_points.txt
prefect_event_process-0.2.3.dist-info/top_level.txt
prefect_event_process-0.2.3.dist-info/RECORD
