Metadata-Version: 2.4
Name: prefect-event-process
Version: 0.2.3
Summary: Prefect Event Driven Process Worker.
Author-email: anilpixel <eziosyanse@gmail.com>
License: Apache License 2.0
Project-URL: Homepage, https://github.com/anilpixel/prefect/tree/main/src/integrations/prefect-event-worker
Keywords: prefect
Classifier: Natural Language :: English
Classifier: Intended Audience :: Developers
Classifier: Intended Audience :: System Administrators
Classifier: License :: OSI Approved :: Apache Software License
Classifier: Programming Language :: Python :: 3 :: Only
Classifier: Programming Language :: Python :: 3.9
Classifier: Programming Language :: Python :: 3.10
Classifier: Programming Language :: Python :: 3.11
Classifier: Programming Language :: Python :: 3.12
Classifier: Programming Language :: Python :: 3.13
Classifier: Topic :: Software Development :: Libraries
Requires-Python: >=3.9
License-File: LICENSE
Requires-Dist: prefect>=3.3.5
Requires-Dist: diskcache>=5.6.0
Dynamic: license-file
